[
null,
{"id":1,"actions":[{"conditionParam1":0,"conditionParam2":0,"conditionType":0,"rating":5,"skillId":1}],"battlerHue":0,"battlerName":"","dropItems":[{"dataId":1,"denominator":1,"kind":0},{"dataId":1,"denominator":1,"kind":0},{"dataId":1,"denominator":1,"kind":0}],"exp":0,"traits":[{"code":22,"dataId":0,"value":0.95},{"code":22,"dataId":1,"value":0.05},{"code":31,"dataId":1,"value":0}],"gold":0,"name":"Placeholder","note":"","params":[200,0,30,30,30,30,30,30]},
{"id":2,"actions":[{"conditionParam1":0,"conditionParam2":0,"conditionType":0,"rating":5,"skillId":1},{"conditionParam1":0,"conditionParam2":0,"conditionType":0,"rating":4,"skillId":12}],"battlerHue":320,"battlerName":"","dropItems":[{"kind":1,"dataId":1,"denominator":20},{"dataId":1,"denominator":1,"kind":0},{"dataId":1,"denominator":1,"kind":0}],"exp":7,"traits":[{"code":22,"dataId":0,"value":0.95},{"code":22,"dataId":1,"value":0.05},{"code":31,"dataId":1,"value":0}],"gold":5,"name":"Cuniculus","note":"<Sideview Battler: Unibun>\n<Sideview Attack Motion: thrust>\n<Scale Sprite: 75%>\n<attack animation: 1>\n<Sideview No Collapse>\n<Sideview Frame Speed: 10>\n","params":[59,100,16,14,10,8,11,5]},
{"id":3,"actions":[{"conditionParam1":0,"conditionParam2":0,"conditionType":0,"rating":5,"skillId":1},{"conditionParam1":0,"conditionParam2":0,"conditionType":0,"rating":4,"skillId":12},{"conditionParam1":0,"conditionParam2":0,"conditionType":0,"rating":5,"skillId":2}],"battlerHue":74,"battlerName":"","dropItems":[{"kind":1,"dataId":6,"denominator":15},{"dataId":1,"denominator":1,"kind":0},{"dataId":1,"denominator":1,"kind":0}],"exp":8,"traits":[{"code":22,"dataId":0,"value":0.95},{"code":22,"dataId":1,"value":0.05},{"code":31,"dataId":1,"value":0}],"gold":4,"name":"Scitterz","note":"<Sideview Battler: Ritz>\n<Breathing>\n<Sideview Attack Motion: thrust>\n<attack animation: 1>\n<Sideview No Collapse>\n<Sideview Frame Speed: 10>\n","params":[69,100,20,12,10,8,14,5]},
{"id":4,"actions":[{"conditionParam1":0,"conditionParam2":0,"conditionType":0,"rating":5,"skillId":1},{"conditionParam1":0,"conditionParam2":0,"conditionType":0,"rating":3,"skillId":13}],"battlerHue":0,"battlerName":"","dropItems":[{"kind":3,"dataId":9,"denominator":3},{"dataId":1,"denominator":1,"kind":0},{"dataId":1,"denominator":1,"kind":0}],"exp":0,"traits":[{"code":22,"dataId":0,"value":0.95},{"code":22,"dataId":1,"value":0.05},{"code":31,"dataId":9,"value":0}],"gold":10,"name":"Ambal Construct","note":"<Sideview Battler: Package2_8>\n<Breathing>\n<Sideview Attack Motion: swing>\n<attack animation: 101>\n<Scale Sprite: 200%>\n<Sideview No Collapse>\n<Sideview Frame Speed: 10>\n","params":[250,150,23,12,14,10,12,6]},
{"id":5,"actions":[{"conditionParam1":0,"conditionParam2":0,"conditionType":0,"rating":5,"skillId":15}],"battlerHue":0,"battlerName":"","dropItems":[{"dataId":1,"denominator":1,"kind":0},{"dataId":1,"denominator":1,"kind":0},{"dataId":1,"denominator":1,"kind":0}],"exp":0,"traits":[{"code":22,"dataId":0,"value":0.95},{"code":22,"dataId":1,"value":0.05},{"code":31,"dataId":9,"value":0}],"gold":0,"name":"King Reustley?","note":"<Sideview Battler: Package2_5>\n<Breathing>\n<Sideview Weapon: 12, thrust, 11>\n<Sideview No Collapse>\n<Sideview Frame Speed: 10>\n","params":[9999,9999,120,120,43,120,1,1]},
{"id":6,"actions":[{"conditionParam1":0,"conditionParam2":1,"conditionType":1,"rating":9,"skillId":14},{"conditionParam1":0,"conditionParam2":0,"conditionType":0,"rating":5,"skillId":16}],"battlerHue":288,"battlerName":"","dropItems":[{"kind":1,"dataId":6,"denominator":15},{"dataId":1,"denominator":1,"kind":0},{"dataId":1,"denominator":1,"kind":0}],"exp":12,"traits":[{"code":22,"dataId":0,"value":0.95},{"code":22,"dataId":1,"value":0.05},{"code":31,"dataId":1,"value":0}],"gold":6,"name":"Ogler","note":"<Sideview Battler: shade-a-watcher_voidling>\n<Sideview Attack Motion: thrust>\n<attack animation: 1>\n<Sideview No Collapse>\n<Sideview Frame Speed: 10>\n","params":[106,100,12,16,19,13,14,5]},
{"id":7,"actions":[{"conditionParam1":0,"conditionParam2":0,"conditionType":0,"rating":5,"skillId":4},{"conditionParam1":0,"conditionParam2":0.25,"conditionType":2,"rating":9,"skillId":8},{"conditionParam1":0,"conditionParam2":0.15,"conditionType":3,"rating":5,"skillId":1}],"battlerHue":287,"battlerName":"","dropItems":[{"kind":3,"dataId":10,"denominator":2},{"dataId":1,"denominator":1,"kind":0},{"dataId":1,"denominator":1,"kind":0}],"exp":20,"traits":[{"code":22,"dataId":0,"value":0.95},{"code":22,"dataId":1,"value":0.05},{"code":31,"dataId":1,"value":0}],"gold":15,"name":"Croaker","note":"<Sideview Battler: inspire-a-shoutfrog_dunecroaker>\n<Sideview Attack Motion: swing>\n<attack animation: 1>\n<Sideview No Collapse>\n<Sideview Frame Speed: 10>\n","params":[350,150,24,18,25,18,18,18]},
{"id":8,"actions":[{"conditionParam1":0,"conditionParam2":0,"conditionType":0,"rating":5,"skillId":1},{"conditionParam1":0,"conditionParam2":0,"conditionType":0,"rating":4,"skillId":17}],"battlerHue":74,"battlerName":"","dropItems":[{"kind":1,"dataId":1,"denominator":8},{"dataId":1,"denominator":1,"kind":0},{"dataId":1,"denominator":1,"kind":0}],"exp":9,"traits":[{"code":22,"dataId":0,"value":0.95},{"code":22,"dataId":1,"value":0.05},{"code":31,"dataId":1,"value":0},{"code":11,"dataId":1,"value":0.5}],"gold":5,"name":"Slime","note":"<Sideview Battler: Slime1_1>\n<Breathing>\n<Sideview Attack Motion: swing>\n<attack animation: 1>\n<Sideview No Collapse>\n<Sideview Frame Speed: 10>\n","params":[64,120,15,9,23,10,12,5]},
{"id":9,"actions":[{"conditionParam1":0,"conditionParam2":0,"conditionType":0,"rating":5,"skillId":1}],"battlerHue":0,"battlerName":"","dropItems":[{"dataId":1,"denominator":1,"kind":0},{"dataId":1,"denominator":1,"kind":0},{"dataId":1,"denominator":1,"kind":0}],"exp":0,"traits":[{"code":22,"dataId":0,"value":0.95},{"code":22,"dataId":1,"value":0.05},{"code":31,"dataId":1,"value":0}],"gold":0,"name":"","note":"","params":[100,0,10,10,10,10,10,10]},
{"id":10,"actions":[{"conditionParam1":0,"conditionParam2":0,"conditionType":0,"rating":5,"skillId":1}],"battlerHue":0,"battlerName":"","dropItems":[{"dataId":1,"denominator":1,"kind":0},{"dataId":1,"denominator":1,"kind":0},{"dataId":1,"denominator":1,"kind":0}],"exp":0,"traits":[{"code":22,"dataId":0,"value":0.95},{"code":22,"dataId":1,"value":0.05},{"code":31,"dataId":1,"value":0}],"gold":0,"name":"","note":"","params":[100,0,10,10,10,10,10,10]},
{"id":11,"actions":[{"conditionParam1":0,"conditionParam2":0,"conditionType":0,"rating":5,"skillId":1}],"battlerHue":0,"battlerName":"","dropItems":[{"dataId":1,"denominator":1,"kind":0},{"dataId":1,"denominator":1,"kind":0},{"dataId":1,"denominator":1,"kind":0}],"exp":0,"traits":[{"code":22,"dataId":0,"value":0.95},{"code":22,"dataId":1,"value":0.05},{"code":31,"dataId":1,"value":0}],"gold":0,"name":"----Kloque Mountain-----","note":"","params":[100,0,10,10,10,10,10,10]},
{"id":12,"actions":[{"conditionParam1":0,"conditionParam2":0,"conditionType":0,"rating":5,"skillId":1},{"conditionParam1":0,"conditionParam2":0,"conditionType":0,"rating":3,"skillId":17}],"battlerHue":0,"battlerName":"","dropItems":[{"kind":1,"dataId":6,"denominator":15},{"dataId":1,"denominator":1,"kind":0},{"dataId":1,"denominator":1,"kind":0}],"exp":15,"traits":[{"code":22,"dataId":0,"value":0.95},{"code":22,"dataId":1,"value":0.05},{"code":31,"dataId":1,"value":0}],"gold":0,"name":"Slime","note":"<Sideview Battler: Slime1_1>\n<Sideview Attack Motion: thrust>\n<Scale Sprite: 75%>\n<attack animation: 1>\n<Sideview No Collapse>\n<Sideview Frame Speed: 10>\n","params":[250,0,25,15,1,15,10,10]},
{"id":13,"actions":[{"conditionParam1":0,"conditionParam2":0,"conditionType":0,"rating":5,"skillId":1},{"conditionParam1":0,"conditionParam2":0,"conditionType":0,"rating":4,"skillId":17}],"battlerHue":0,"battlerName":"","dropItems":[{"kind":1,"dataId":6,"denominator":3},{"dataId":1,"denominator":1,"kind":0},{"dataId":1,"denominator":1,"kind":0}],"exp":50,"traits":[{"code":22,"dataId":0,"value":0.95},{"code":22,"dataId":1,"value":0.05},{"code":31,"dataId":1,"value":0}],"gold":15,"name":"Large Slime","note":"<Sideview Battler: Slime1_1>\n<Sideview Attack Motion: thrust>\n<Scale Sprite: 300%>\n<attack animation: 1>\n<Sideview No Collapse>\n<Sideview Frame Speed: 10>","params":[800,150,32,20,1,20,10,10]},
{"id":14,"actions":[{"conditionParam1":0,"conditionParam2":0,"conditionType":0,"rating":5,"skillId":1}],"battlerHue":0,"battlerName":"","dropItems":[{"dataId":1,"denominator":1,"kind":0},{"dataId":1,"denominator":1,"kind":0},{"dataId":1,"denominator":1,"kind":0}],"exp":0,"traits":[{"code":22,"dataId":0,"value":0.95},{"code":22,"dataId":1,"value":0.05},{"code":31,"dataId":1,"value":0}],"gold":0,"name":"","note":"","params":[100,0,10,10,10,10,10,10]},
{"id":15,"actions":[{"conditionParam1":0,"conditionParam2":0,"conditionType":0,"rating":5,"skillId":1}],"battlerHue":0,"battlerName":"","dropItems":[{"dataId":1,"denominator":1,"kind":0},{"dataId":1,"denominator":1,"kind":0},{"dataId":1,"denominator":1,"kind":0}],"exp":0,"traits":[{"code":22,"dataId":0,"value":0.95},{"code":22,"dataId":1,"value":0.05},{"code":31,"dataId":1,"value":0}],"gold":0,"name":"","note":"","params":[100,0,10,10,10,10,10,10]},
{"id":16,"actions":[{"conditionParam1":0,"conditionParam2":0,"conditionType":0,"rating":5,"skillId":1}],"battlerHue":0,"battlerName":"","dropItems":[{"dataId":1,"denominator":1,"kind":0},{"dataId":1,"denominator":1,"kind":0},{"dataId":1,"denominator":1,"kind":0}],"exp":0,"traits":[{"code":22,"dataId":0,"value":0.95},{"code":22,"dataId":1,"value":0.05},{"code":31,"dataId":1,"value":0}],"gold":0,"name":"","note":"","params":[100,0,10,10,10,10,10,10]},
{"id":17,"actions":[{"conditionParam1":0,"conditionParam2":0,"conditionType":0,"rating":5,"skillId":1}],"battlerHue":0,"battlerName":"","dropItems":[{"dataId":1,"denominator":1,"kind":0},{"dataId":1,"denominator":1,"kind":0},{"dataId":1,"denominator":1,"kind":0}],"exp":0,"traits":[{"code":22,"dataId":0,"value":0.95},{"code":22,"dataId":1,"value":0.05},{"code":31,"dataId":1,"value":0}],"gold":0,"name":"","note":"","params":[100,0,10,10,10,10,10,10]},
{"id":18,"actions":[{"conditionParam1":0,"conditionParam2":0,"conditionType":0,"rating":5,"skillId":1}],"battlerHue":0,"battlerName":"","dropItems":[{"dataId":1,"denominator":1,"kind":0},{"dataId":1,"denominator":1,"kind":0},{"dataId":1,"denominator":1,"kind":0}],"exp":0,"traits":[{"code":22,"dataId":0,"value":0.95},{"code":22,"dataId":1,"value":0.05},{"code":31,"dataId":1,"value":0}],"gold":0,"name":"","note":"","params":[100,0,10,10,10,10,10,10]},
{"id":19,"actions":[{"conditionParam1":0,"conditionParam2":0,"conditionType":0,"rating":5,"skillId":1}],"battlerHue":0,"battlerName":"","dropItems":[{"dataId":1,"denominator":1,"kind":0},{"dataId":1,"denominator":1,"kind":0},{"dataId":1,"denominator":1,"kind":0}],"exp":0,"traits":[{"code":22,"dataId":0,"value":0.95},{"code":22,"dataId":1,"value":0.05},{"code":31,"dataId":1,"value":0}],"gold":0,"name":"","note":"","params":[100,0,10,10,10,10,10,10]},
{"id":20,"actions":[{"conditionParam1":0,"conditionParam2":0,"conditionType":0,"rating":5,"skillId":1}],"battlerHue":0,"battlerName":"","dropItems":[{"dataId":1,"denominator":1,"kind":0},{"dataId":1,"denominator":1,"kind":0},{"dataId":1,"denominator":1,"kind":0}],"exp":0,"traits":[{"code":22,"dataId":0,"value":0.95},{"code":22,"dataId":1,"value":0.05},{"code":31,"dataId":1,"value":0}],"gold":0,"name":"","note":"","params":[100,0,10,10,10,10,10,10]},
{"id":21,"actions":[{"conditionParam1":0,"conditionParam2":0,"conditionType":0,"rating":5,"skillId":1}],"battlerHue":0,"battlerName":"","dropItems":[{"dataId":1,"denominator":1,"kind":0},{"dataId":1,"denominator":1,"kind":0},{"dataId":1,"denominator":1,"kind":0}],"exp":0,"traits":[{"code":22,"dataId":0,"value":0.95},{"code":22,"dataId":1,"value":0.05},{"code":31,"dataId":1,"value":0}],"gold":0,"name":"","note":"","params":[100,0,10,10,10,10,10,10]},
{"id":22,"actions":[{"conditionParam1":0,"conditionParam2":0,"conditionType":0,"rating":5,"skillId":1}],"battlerHue":0,"battlerName":"","dropItems":[{"dataId":1,"denominator":1,"kind":0},{"dataId":1,"denominator":1,"kind":0},{"dataId":1,"denominator":1,"kind":0}],"exp":0,"traits":[{"code":22,"dataId":0,"value":0.95},{"code":22,"dataId":1,"value":0.05},{"code":31,"dataId":1,"value":0}],"gold":0,"name":"","note":"","params":[100,0,10,10,10,10,10,10]},
{"id":23,"actions":[{"conditionParam1":0,"conditionParam2":0,"conditionType":0,"rating":5,"skillId":1}],"battlerHue":0,"battlerName":"","dropItems":[{"dataId":1,"denominator":1,"kind":0},{"dataId":1,"denominator":1,"kind":0},{"dataId":1,"denominator":1,"kind":0}],"exp":0,"traits":[{"code":22,"dataId":0,"value":0.95},{"code":22,"dataId":1,"value":0.05},{"code":31,"dataId":1,"value":0}],"gold":0,"name":"","note":"","params":[100,0,10,10,10,10,10,10]},
{"id":24,"actions":[{"conditionParam1":0,"conditionParam2":0,"conditionType":0,"rating":5,"skillId":1}],"battlerHue":0,"battlerName":"","dropItems":[{"dataId":1,"denominator":1,"kind":0},{"dataId":1,"denominator":1,"kind":0},{"dataId":1,"denominator":1,"kind":0}],"exp":0,"traits":[{"code":22,"dataId":0,"value":0.95},{"code":22,"dataId":1,"value":0.05},{"code":31,"dataId":1,"value":0}],"gold":0,"name":"","note":"","params":[100,0,10,10,10,10,10,10]},
{"id":25,"actions":[{"conditionParam1":0,"conditionParam2":0,"conditionType":0,"rating":5,"skillId":1}],"battlerHue":0,"battlerName":"","dropItems":[{"dataId":1,"denominator":1,"kind":0},{"dataId":1,"denominator":1,"kind":0},{"dataId":1,"denominator":1,"kind":0}],"exp":0,"traits":[{"code":22,"dataId":0,"value":0.95},{"code":22,"dataId":1,"value":0.05},{"code":31,"dataId":1,"value":0}],"gold":0,"name":"","note":"","params":[100,0,10,10,10,10,10,10]}
]